README.md
setup.py
cheesefactory_smb/__init__.py
cheesefactory_smb.egg-info/PKG-INFO
cheesefactory_smb.egg-info/SOURCES.txt
cheesefactory_smb.egg-info/dependency_links.txt
cheesefactory_smb.egg-info/requires.txt
cheesefactory_smb.egg-info/top_level.txt