Metadata-Version: 2.1
Name: cheesefactory-smb
Version: 0.4
Summary: A simple wrapper for PySMB.
Home-page: https://bitbucket.org/hellsgrannies/cheesefactory-smb
Author: Todd Salazar
Author-email: unixsal@yahoo.com
License: UNKNOWN
Keywords: cheesefactory smb development
Platform: UNKNOWN
Classifier: Development Status :: 4 - Beta
Classifier: Intended Audience :: Developers
Classifier: License :: OSI Approved :: BSD License
Classifier: Programming Language :: Python :: 3.6
Classifier: Programming Language :: Python :: 3.7
Classifier: Programming Language :: Python :: 3.8
